{
  "schema": "scientific_figure_reconstruction.v1",
  "id": "reference-08-neuropixels-central-heatmap-C",
  "source": {
    "path": "../../assets/reference/reference-08-neuropixels-central-heatmap-C-reference.png",
    "usage": "QA-only reference view; not used by generated candidate layers.",
    "notes": "Single panel C heatmap reconstructed from visual inspection. Dense activity field is generated from editable recipes and does not sample or reuse the source raster."
  },
  "canvas": {
    "width": 636,
    "height": 605,
    "background": "#ffffff"
  },
  "typography": {
    "fontFamily": "Arial, Helvetica, sans-serif",
    "defaultSize": 12,
    "color": "#111111",
    "fontImports": [],
    "fontFaces": [],
    "fontCandidates": [
      "Arial",
      "Helvetica",
      "Arimo",
      "Source Sans 3",
      "Roboto",
      "Noto Sans"
    ],
    "calibration": {
      "fontStretch": "normal",
      "letterSpacing": 0,
      "lineHeight": 1.05,
      "notes": "First-pass visual match; title and labels use Arial-like bold sans without source-raster text extraction."
    }
  },
  "coordinateSystems": [
    {
      "id": "panel-c.xy",
      "type": "cartesian",
      "xDomain": [
        0,
        200
      ],
      "yDomain": [
        1,
        384
      ],
      "plotBbox": {
        "x": 84,
        "y": 25,
        "width": 541,
        "height": 564
      }
    },
    {
      "id": "panel-c.activity-z",
      "type": "colorScale",
      "domain": [
        -2.2,
        2.4
      ],
      "stops": [
        {
          "value": -2.2,
          "color": "#001316"
        },
        {
          "value": -0.7,
          "color": "#08282b"
        },
        {
          "value": 0,
          "color": "#101311"
        },
        {
          "value": 0.8,
          "color": "#8a6200"
        },
        {
          "value": 2.4,
          "color": "#f1bb18"
        }
      ]
    }
  ],
  "panels": [
    {
      "id": "panel-c",
      "label": {
        "id": "panel-c-label",
        "text": "C",
        "x": 42,
        "y": 10,
        "fontSize": 21,
        "fontWeight": 700,
        "anchor": "middle"
      },
      "title": {
        "id": "panel-c-title",
        "text": "Sorted neural activity (z-scored firing rate)",
        "x": 72,
        "y": 10,
        "fontSize": 16,
        "fontWeight": 700,
        "anchor": "start",
        "sourceBox": {
          "x": 72,
          "y": 0,
          "width": 363,
          "height": 18
        },
        "fit": "measured first-pass"
      },
      "bbox": {
        "x": 0,
        "y": 0,
        "width": 636,
        "height": 605
      },
      "plot": {
        "dataBbox": {
          "x": 84,
          "y": 25,
          "width": 541,
          "height": 564
        },
        "background": "#071214",
        "axes": {
          "xAxis": {
            "id": "panel-c-x-axis",
            "sourceCalibrated": true,
            "originAlignment": {
              "id": "panel-c-x-origin-row-strip-alignment",
              "tickValue": 0,
              "target": "panel-c-row-block-strip.right",
              "deltaPx": 2,
              "semantic": "The x=0 tick is the plot-origin tick immediately to the right of the row-block strip."
            },
            "line": {
              "x1": 84,
              "y1": 589,
              "x2": 625,
              "y2": 589
            },
            "tickLength": 7,
            "stroke": "#111111",
            "strokeWidth": 1,
            "provenance": {
              "confidence": "high",
              "note": "Explicit x-axis line measured from the source crop; kept separate from heatmap dataBbox for editable offset-axis rendering."
            }
          },
          "yAxis": {
            "id": "panel-c-y-axis",
            "sourceCalibrated": true,
            "line": {
              "x1": 62,
              "y1": 25,
              "x2": 62,
              "y2": 589
            },
            "tickLabelBand": {
              "id": "panel-c-y-tick-label-band",
              "x": 33,
              "y": 25,
              "width": 24,
              "height": 564
            },
            "tickLength": 5,
            "stroke": "#111111",
            "strokeWidth": 1,
            "provenance": {
              "confidence": "high",
              "note": "Explicit y-axis line measured from the source crop and intentionally offset left of the row-block side strip."
            }
          }
        },
        "x": {
          "scale": "linear",
          "domain": [
            0,
            200
          ],
          "ticks": [
            {
              "value": 0,
              "label": "0",
              "anchorTo": "panel-c.plot.dataBbox.left",
              "alignment": {
                "id": "panel-c-x-tick-0-row-strip-alignment",
                "target": "panel-c-row-block-strip.right",
                "deltaPx": 2,
                "semantic": "Plot origin tick aligned with the heatmap left edge and offset two pixels to the right of the side row-block strip."
              }
            },
            {
              "value": 50,
              "label": "50"
            },
            {
              "value": 100,
              "label": "100"
            },
            {
              "value": 150,
              "label": "150"
            },
            {
              "value": 200,
              "label": "200"
            }
          ],
          "label": null
        },
        "y": {
          "scale": "linear",
          "domain": [
            1,
            384
          ],
          "ticks": [
            {
              "value": 1,
              "label": "1"
            },
            {
              "value": 96,
              "label": "96"
            },
            {
              "value": 192,
              "label": "192"
            },
            {
              "value": 288,
              "label": "288"
            },
            {
              "value": 336,
              "label": "336"
            },
            {
              "value": 384,
              "label": "384"
            }
          ],
          "label": {
            "id": "panel-c-y-label",
            "text": "Neuron # (sorted by peak location)",
            "x": 13,
            "y": 306,
            "rotation": -90,
            "fontSize": 16,
            "fontWeight": 400,
            "anchor": "middle",
            "anchorTo": "panel-c-y-tick-label-band",
            "sourceBox": {
              "x": 18,
              "y": 207,
              "width": 17,
              "height": 211
            }
          }
        }
      },
      "layoutObjects": [
        {
          "id": "panel-c-row-block-strip",
          "type": "sideRowBlockStrip",
          "orientation": "vertical",
          "bbox": {
            "x": 69,
            "y": 25,
            "width": 13,
            "height": 564
          },
          "sharedLayoutFrame": "panel-c.plot.dataBbox",
          "alignments": [
            {
              "id": "panel-c-row-strip-top-to-data-top",
              "sourceEdge": "top",
              "target": "panel-c.plot.dataBbox.top",
              "deltaPx": 0
            },
            {
              "id": "panel-c-row-strip-bottom-to-data-bottom",
              "sourceEdge": "bottom",
              "target": "panel-c.plot.dataBbox.bottom",
              "deltaPx": 0
            },
            {
              "id": "panel-c-row-strip-right-to-data-left",
              "sourceEdge": "right",
              "target": "panel-c.plot.dataBbox.left",
              "deltaPx": -2,
              "semantic": "The row-block strip terminates immediately before the heatmap/x-axis origin; the x=0 tick resolves from the data frame, not the strip."
            }
          ],
          "exclusionZone": {
            "paddingPx": 1
          },
          "expectedComponentCount": 6,
          "components": [
            {
              "id": "left-dark-edge",
              "kind": "border",
              "bbox": {"x": 69, "y": 25, "width": 2, "height": 564},
              "fill": "#111111"
            },
            {
              "id": "upper-teal-component",
              "kind": "segment",
              "bbox": {"x": 71, "y": 25, "width": 11, "height": 283},
              "fill": "#087b76"
            },
            {
              "id": "light-cyan-transition-component",
              "kind": "segment",
              "bbox": {"x": 71, "y": 308, "width": 11, "height": 132},
              "fill": "#8fd9cf"
            },
            {
              "id": "upper-gold-component",
              "kind": "segment",
              "bbox": {"x": 71, "y": 440, "width": 11, "height": 70},
              "fill": "#e9a22f"
            },
            {
              "id": "thin-gold-boundary-rule",
              "kind": "separator",
              "bbox": {"x": 71, "y": 510, "width": 11, "height": 2},
              "fill": "#f2b03d"
            },
            {
              "id": "lower-orange-component",
              "kind": "segment",
              "bbox": {"x": 71, "y": 512, "width": 11, "height": 77},
              "fill": "#c97908"
            }
          ],
          "segments": [
            {
              "id": "upper-teal-block",
              "fromY": 25,
              "toY": 308,
              "fill": "#087b76",
              "label": "upper sorted block"
            },
            {
              "id": "light-cyan-transition-block",
              "fromY": 308,
              "toY": 440,
              "fill": "#8fd9cf",
              "label": "light separator/transition block"
            },
            {
              "id": "upper-gold-block",
              "fromY": 440,
              "toY": 510,
              "fill": "#e9a22f",
              "label": "upper lower sorted block"
            },
            {
              "id": "lower-orange-block",
              "fromY": 512,
              "toY": 589,
              "fill": "#c97908",
              "label": "bottom sorted block"
            }
          ],
          "separators": [
            {
              "id": "row-block-gold-orange-boundary",
              "atY": 510,
              "stroke": "#f2b03d",
              "strokeWidth": 1.2
            }
          ],
          "borders": [
            {
              "side": "left",
              "width": 2,
              "fill": "#101010"
            }
          ],
          "linkedAxis": "panel-c-y-axis"
        }
      ],
      "marks": [
        {
          "id": "panel-c-heatmap",
          "type": "heatmap",
          "renderer": "canvas",
          "usesTransform": "panel-c.xy",
          "colorScale": "panel-c.activity-z",
          "matrix": {
            "rows": 384,
            "columns": 200
          },
          "interpolation": false,
          "recipe": {
            "type": "syntheticSortedNeuralActivity",
            "seed": 8108,
            "baseline": -0.15,
            "noise": 0.56,
            "horizontalLineProbability": 0.78,
            "rowTextureStrength": 0.72,
            "columnBandStrength": 0.32,
            "eventResponses": [
              {
                "centerX": 50,
                "centerY": 132,
                "sigmaX": 8,
                "sigmaY": 58,
                "amplitude": 1.75
              },
              {
                "centerX": 50,
                "centerY": 268,
                "sigmaX": 6,
                "sigmaY": 42,
                "amplitude": 1.35
              },
              {
                "centerX": 50,
                "centerY": 344,
                "sigmaX": 11,
                "sigmaY": 42,
                "amplitude": 1.1
              },
              {
                "centerX": 150,
                "centerY": 92,
                "sigmaX": 9,
                "sigmaY": 54,
                "amplitude": 1.25
              },
              {
                "centerX": 150,
                "centerY": 244,
                "sigmaX": 7,
                "sigmaY": 58,
                "amplitude": 1.6
              },
              {
                "centerX": 166,
                "centerY": 170,
                "sigmaX": 15,
                "sigmaY": 48,
                "amplitude": 1.22
              },
              {
                "centerX": 22,
                "centerY": 218,
                "sigmaX": 14,
                "sigmaY": 24,
                "amplitude": 0.95
              },
              {
                "centerX": 32,
                "centerY": 368,
                "sigmaX": 12,
                "sigmaY": 26,
                "amplitude": 0.92
              }
            ],
            "cyanSuppressions": [
              {
                "centerX": 94,
                "centerY": 32,
                "sigmaX": 18,
                "sigmaY": 33,
                "amplitude": -1.24
              },
              {
                "centerX": 93,
                "centerY": 193,
                "sigmaX": 23,
                "sigmaY": 13,
                "amplitude": -1.15
              },
              {
                "centerX": 103,
                "centerY": 339,
                "sigmaX": 17,
                "sigmaY": 11,
                "amplitude": -1
              },
              {
                "centerX": 182,
                "centerY": 31,
                "sigmaX": 20,
                "sigmaY": 28,
                "amplitude": -1.04
              },
              {
                "centerX": 184,
                "centerY": 195,
                "sigmaX": 22,
                "sigmaY": 13,
                "amplitude": -1
              },
              {
                "centerX": 184,
                "centerY": 340,
                "sigmaX": 19,
                "sigmaY": 10,
                "amplitude": -0.95
              }
            ]
          }
        },
        {
          "id": "panel-c-event-lines",
          "type": "eventLines",
          "renderer": "svg",
          "usesTransform": "panel-c.xy",
          "values": [
            50,
            100,
            150
          ],
          "stroke": "#e8e8e8",
          "strokeWidth": 1.5,
          "dasharray": "9 7",
          "opacity": 0.95
        }
      ],
      "annotations": [],
      "provenance": [
        {
          "target": "panel-c-heatmap",
          "confidence": "medium",
          "note": "Activity clusters, noise density, and row ordering are approximate semantic recipes intended for editable first-pass visual inspection."
        },
        {
          "target": "panel-c.axes",
          "confidence": "high",
          "note": "Plot box, ticks, event anchors, title, y-label, and color strip positions were visually measured from the 636 x 605 reference crop."
        }
      ]
    }
  ],
  "validation": {
    "expected": {
      "canvasWidth": 636,
      "canvasHeight": 605,
      "panelCount": 1,
      "eventLineCount": 3,
      "xTickCount": 5,
      "yTickCount": 6,
      "qaSourceUsage": "reference-only"
    },
    "constraints": [
      "Generated candidate must not call drawImage with the source raster.",
      "Generated candidate must not use the source raster as a CSS background.",
      "Event lines at x=50, x=100, and x=150 share the panel-c.xy transform.",
      "Heatmap data, row-block side strip, strip separator, strip border, offset y-axis, ticks, tick-label band, and y-axis title are distinct semantic layout objects."
    ]
  },
  "confidence": [
    {
      "target": "overall",
      "confidence": "first-pass",
      "note": "Close structural reconstruction; exact neural activity values are inferred texture recipes, not recovered data."
    }
  ]
}
